mlx_catalog_connector/__init__.py
mlx_catalog_connector/_version.py
mlx_catalog_connector/mlx-catalog.json
mlx_catalog_connector/mlx_component_catalog_connector.py
mlx_catalog_connector/mlx_schema_provider.py
mlx_component_catalog_connector-0.1.1.dist-info/METADATA
mlx_component_catalog_connector-0.1.1.dist-info/WHEEL
mlx_component_catalog_connector-0.1.1.dist-info/entry_points.txt
mlx_component_catalog_connector-0.1.1.dist-info/top_level.txt
mlx_component_catalog_connector-0.1.1.dist-info/RECORD
